dynatrace/opentelemetry/metrics/export/__init__.py
dynatrace/opentelemetry/metrics/export/_exporter.py
dynatrace/opentelemetry/metrics/export/_factory.py
dynatrace/opentelemetry/metrics/export/_histogram_utils.py
opentelemetry_exporter_dynatrace_metrics-1.0.3.dist-info/LICENSE
opentelemetry_exporter_dynatrace_metrics-1.0.3.dist-info/METADATA
opentelemetry_exporter_dynatrace_metrics-1.0.3.dist-info/WHEEL
opentelemetry_exporter_dynatrace_metrics-1.0.3.dist-info/entry_points.txt
opentelemetry_exporter_dynatrace_metrics-1.0.3.dist-info/top_level.txt
opentelemetry_exporter_dynatrace_metrics-1.0.3.dist-info/RECORD
