Metadata-Version: 2.1
Name: opentelemetry-exporter-dynatrace-metrics
Version: 1.0.3
Summary: Dynatrace Metric Exporter for OpenTelemetry
Home-page: https://github.com/dynatrace-oss/opentelemetry-metric-python/
Author: Dynatrace
Author-email: opensource@dynatrace.com
License: Apache-2.0
Project-URL: Dynatrace, https://www.dynatrace.com/
Project-URL: Source, https://github.com/dynatrace-oss/opentelemetry-metric-python/
Project-URL: Download, https://pypi.org/project/opentelemetry-exporter-dynatrace-metrics/#files
Platform: any
Classifier: Development Status :: 7 - Inactive
Classifier: Intended Audience :: Developers
Classifier: License :: OSI Approved :: Apache Software License
Classifier: Operating System :: OS Independent
Classifier: Programming Language :: Python
Classifier: Programming Language :: Python :: 3
Classifier: Programming Language :: Python :: 3.7
Classifier: Programming Language :: Python :: 3.8
Classifier: Programming Language :: Python :: 3.9
Classifier: Programming Language :: Python :: 3.10
Classifier: Programming Language :: Python :: Implementation :: CPython
Classifier: Programming Language :: Python :: Implementation :: PyPy
Classifier: Topic :: System :: Monitoring
Requires-Python: >=3.7
Requires-Dist: opentelemetry-api ~=1.12
Requires-Dist: opentelemetry-sdk ~=1.12
Requires-Dist: requests ~=2.25
Requires-Dist: dynatrace-metric-utils ~=0.2.1
